flask_dantic/__init__.py
flask_dantic/model.py
flask_dantic/space.py
fdantic-0.1.0.dist-info/METADATA
fdantic-0.1.0.dist-info/WHEEL
fdantic-0.1.0.dist-info/top_level.txt
fdantic-0.1.0.dist-info/RECORD
