Metadata-Version: 2.1
Name: fdantic
Version: 0.1.0
Summary: Extenção flask para aumento de agilidade de criação de formulario para o flask-restx no processo de criação de projeto.
Home-page: https://github.com/feiticeiro-tec/feiticeiro-tec
Author: Silvio Henrique Cruz Da Silva
Author-email: silviohenriquecruzdasilva@gmail.com
License: BSD3
Keywords: Pacote
Requires-Dist: flask
Requires-Dist: flask-restx
Requires-Dist: pydantic
